codefest/cf07/hdl/synth_top.sv
`timescale 1ns/1ps

/*
 * Module: compute_core
 *
 * Purpose:
 *   Multi-cycle INT8 dot-product compute block for the project accelerator's
 *   dominant 3x3 convolution kernel. The M2 core models one 3x3 lane
 *   (9 activation/weight products) with INT32 accumulation.
 *
 * Clocking and reset:
 *   Single clock domain: clk.
 *   Reset is synchronous, active high.
 *
 * Ports:
 *   clk          input   1 bit               System clock.
 *   rst          input   1 bit               Synchronous active-high reset.
 *   start        input   1 bit               Pulse high for one cycle to start.
 *   activations  input   TAPS*DATA_WIDTH     Packed signed INT8 activations.
 *   weights      input   TAPS*DATA_WIDTH     Packed signed INT8 weights.
 *   bias         input   ACC_WIDTH           Signed INT32 initial accumulator.
 *   busy         output  1 bit               High while products are accumulated.
 *   done         output  1 bit               One-cycle pulse when result is valid.
 *   result       output  ACC_WIDTH           Signed INT32 dot-product result.
 */
module compute_core #(
    parameter int TAPS = 9,
    parameter int DATA_WIDTH = 8,
    parameter int ACC_WIDTH = 32
) (
    input  logic                                  clk,
    input  logic                                  rst,
    input  logic                                  start,
    input  logic signed [TAPS*DATA_WIDTH-1:0]    activations,
    input  logic signed [TAPS*DATA_WIDTH-1:0]    weights,
    input  logic signed [ACC_WIDTH-1:0]          bias,
    output logic                                  busy,
    output logic                                  done,
    output logic signed [ACC_WIDTH-1:0]          result
);

    localparam int TAP_INDEX_WIDTH = (TAPS <= 1) ? 1 : $clog2(TAPS);

    logic [TAP_INDEX_WIDTH-1:0] tap_index;
    logic signed [ACC_WIDTH-1:0] accumulator;
    logic signed [DATA_WIDTH-1:0] activation_tap;
    logic signed [DATA_WIDTH-1:0] weight_tap;
    logic signed [(2*DATA_WIDTH)-1:0] product;
    logic signed [ACC_WIDTH-1:0] product_ext;
    logic signed [ACC_WIDTH-1:0] next_accumulator;

    assign activation_tap = activations[tap_index*DATA_WIDTH +: DATA_WIDTH];
    assign weight_tap = weights[tap_index*DATA_WIDTH +: DATA_WIDTH];
    assign product = activation_tap * weight_tap;
    assign product_ext = {{(ACC_WIDTH-(2*DATA_WIDTH)){product[(2*DATA_WIDTH)-1]}}, product};
    assign next_accumulator = accumulator + product_ext;

    always_ff @(posedge clk) begin
        if (rst) begin
            tap_index <= '0;
            accumulator <= '0;
            result <= '0;
            busy <= 1'b0;
            done <= 1'b0;
        end else begin
            done <= 1'b0;

            if (start && !busy) begin
                tap_index <= '0;
                accumulator <= bias;
                busy <= 1'b1;
            end else if (busy) begin
                accumulator <= next_accumulator;

                if (tap_index == TAPS-1) begin
                    result <= next_accumulator;
                    busy <= 1'b0;
                    done <= 1'b1;
                end else begin
                    tap_index <= tap_index + 1'b1;
                end
            end
        end
    end

endmodule

project/m2/rtl/interface.sv
`timescale 1ns/1ps

/*
 * Module: axis_interface
 *
 * Purpose:
 *   Minimal AXI4-Stream command/response interface for the M2 accelerator
 *   prototype. This module matches the M1-selected AXI4-Stream transport and
 *   demonstrates complete TVALID/TREADY write and read/response transactions.
 *
 * Clocking and reset:
 *   Single clock domain: clk.
 *   Reset is synchronous, active high.
 *
 * AXI4-Stream contract:
 *   A transfer occurs only when TVALID and TREADY are both high on a rising
 *   clk edge. Source-side payloads remain stable while TVALID is high and
 *   TREADY is low. This module deasserts s_axis_tready while a response is
 *   pending so no command is dropped.
 *
 * Transaction format:
 *   s_axis_tdata[31:28] = opcode
 *     4'h1: WRITE_CONFIG. s_axis_tdata[27:0] is stored in config_reg.
 *     4'h2: READ_CONFIG.  Emits one response word on m_axis_tdata.
 *   s_axis_tdata[27:0] = payload
 *   m_axis_tdata response = {4'hA, config_reg}
 *
 * Ports:
 *   clk           input   1 bit      System clock.
 *   rst           input   1 bit      Synchronous active-high reset.
 *   s_axis_tdata  input   32 bits    Command stream payload.
 *   s_axis_tvalid input   1 bit      Command stream valid.
 *   s_axis_tready output  1 bit      Command stream ready.
 *   s_axis_tlast  input   1 bit      Command packet terminator; single-word commands use 1.
 *   m_axis_tdata  output  32 bits    Response stream payload.
 *   m_axis_tvalid output  1 bit      Response stream valid.
 *   m_axis_tready input   1 bit      Response stream ready.
 *   m_axis_tlast  output  1 bit      Response packet terminator; responses are one word.
 *   config_reg    output  28 bits    Stored configuration payload for debug/status.
 */
module axis_interface (
    input  logic        clk,
    input  logic        rst,
    input  logic [31:0] s_axis_tdata,
    input  logic        s_axis_tvalid,
    output logic        s_axis_tready,
    input  logic        s_axis_tlast,
    output logic [31:0] m_axis_tdata,
    output logic        m_axis_tvalid,
    input  logic        m_axis_tready,
    output logic        m_axis_tlast,
    output logic [27:0] config_reg
);

    localparam logic [3:0] OPCODE_WRITE_CONFIG = 4'h1;
    localparam logic [3:0] OPCODE_READ_CONFIG  = 4'h2;
    localparam logic [3:0] OPCODE_RESPONSE     = 4'hA;

    logic [3:0] opcode;
    logic [27:0] payload;
    logic input_handshake;
    logic output_handshake;

    assign opcode = s_axis_tdata[31:28];
    assign payload = s_axis_tdata[27:0];
    assign s_axis_tready = !m_axis_tvalid;
    assign input_handshake = s_axis_tvalid && s_axis_tready;
    assign output_handshake = m_axis_tvalid && m_axis_tready;

    always_ff @(posedge clk) begin
        if (rst) begin
            config_reg <= 28'd0;
            m_axis_tdata <= 32'd0;
            m_axis_tvalid <= 1'b0;
            m_axis_tlast <= 1'b0;
        end else begin
            if (output_handshake) begin
                m_axis_tvalid <= 1'b0;
                m_axis_tlast <= 1'b0;
            end

            if (input_handshake && s_axis_tlast) begin
                if (opcode == OPCODE_WRITE_CONFIG) begin
                    config_reg <= payload;
                end else if (opcode == OPCODE_READ_CONFIG) begin
                    m_axis_tdata <= {OPCODE_RESPONSE, config_reg};
                    m_axis_tvalid <= 1'b1;
                    m_axis_tlast <= 1'b1;
                end
            end
        end
    end

endmodule

project/m3/rtl/top.sv
`timescale 1ns/1ps

/*
 * Module: top
 *
 * Purpose:
 *   Milestone 3 integrated accelerator top. The module instantiates the M2
 *   AXI4-Stream interface (`axis_interface`) and the M2 INT8 dot-product
 *   compute core (`compute_core`) and connects them with command-decoding glue.
 *
 * External ports:
 *   clk           input   1 bit      System clock; all logic is single-domain.
 *   rst           input   1 bit      Synchronous active-high reset.
 *   s_axis_tdata  input   32 bits    Host command stream payload.
 *   s_axis_tvalid input   1 bit      Host command stream valid.
 *   s_axis_tready output  1 bit      Host command stream ready.
 *   s_axis_tlast  input   1 bit      Host command packet terminator.
 *   m_axis_tdata  output  32 bits    Host response stream payload.
 *   m_axis_tvalid output  1 bit      Host response stream valid.
 *   m_axis_tready input   1 bit      Host response stream ready.
 *   m_axis_tlast  output  1 bit      Host response packet terminator.
 *   compute_busy  output  1 bit      Debug/status: compute core is active.
 *   compute_done  output  1 bit      Debug/status: one-cycle result-valid pulse.
 *
 * Host command format:
 *   s_axis_tdata[31:28] = 4'h1 for all writes accepted by the M2 interface.
 *   s_axis_tdata[27:24] = M3 subcommand.
 *     4'h0: LOAD_ACTIVATION, payload[23:20] = tap index, payload[7:0] = INT8.
 *     4'h1: LOAD_WEIGHT,     payload[23:20] = tap index, payload[7:0] = INT8.
 *     4'h2: LOAD_BIAS_LO,    payload[15:0]  = bias[15:0].
 *     4'h3: LOAD_BIAS_HI,    payload[15:0]  = bias[31:16].
 *     4'h4: START, starts the 9-tap dot product when the core is idle.
 *     4'h5: READ_RESULT, emits {4'hB, result[27:0]} when result_valid is set.
 *
 * Glue logic:
 *   The M2 interface accepts and backpressures host writes. This top-level
 *   glue observes completed write handshakes, packs activation/weight/bias
 *   registers, pulses compute_core.start, latches compute_core.result, and
 *   muxes a one-word result response onto the host response stream.
 */
module top (
    input  logic        clk,
    input  logic        rst,
    input  logic [31:0] s_axis_tdata,
    input  logic        s_axis_tvalid,
    output logic        s_axis_tready,
    input  logic        s_axis_tlast,
    output logic [31:0] m_axis_tdata,
    output logic        m_axis_tvalid,
    input  logic        m_axis_tready,
    output logic        m_axis_tlast,
    output logic        compute_busy,
    output logic        compute_done
);

    localparam int TAPS = 9;
    localparam int DATA_WIDTH = 8;
    localparam int ACC_WIDTH = 32;

    localparam logic [3:0] OPCODE_WRITE_CONFIG = 4'h1;
    localparam logic [3:0] RESP_RESULT         = 4'hB;

    localparam logic [3:0] CMD_LOAD_ACTIVATION = 4'h0;
    localparam logic [3:0] CMD_LOAD_WEIGHT     = 4'h1;
    localparam logic [3:0] CMD_LOAD_BIAS_LO    = 4'h2;
    localparam logic [3:0] CMD_LOAD_BIAS_HI    = 4'h3;
    localparam logic [3:0] CMD_START           = 4'h4;
    localparam logic [3:0] CMD_READ_RESULT     = 4'h5;

    logic [31:0] interface_m_axis_tdata;
    logic        interface_m_axis_tvalid;
    logic        interface_m_axis_tlast;
    logic [27:0] interface_config_reg;

    logic signed [TAPS*DATA_WIDTH-1:0] activations;
    logic signed [TAPS*DATA_WIDTH-1:0] weights;
    logic signed [ACC_WIDTH-1:0]       bias;
    logic                              start;
    logic signed [ACC_WIDTH-1:0]       result;
    logic signed [ACC_WIDTH-1:0]       result_latched;
    logic                              result_valid;
    logic                              result_response_valid;

    logic command_handshake;
    logic [3:0] opcode;
    logic [3:0] subcommand;
    logic [3:0] tap_index;
    logic signed [7:0] data_byte;

    assign opcode = s_axis_tdata[31:28];
    assign subcommand = s_axis_tdata[27:24];
    assign tap_index = s_axis_tdata[23:20];
    assign data_byte = s_axis_tdata[7:0];
    assign command_handshake = s_axis_tvalid && s_axis_tready && s_axis_tlast &&
                               (opcode == OPCODE_WRITE_CONFIG);

    assign m_axis_tdata = result_response_valid ? {RESP_RESULT, result_latched[27:0]} :
                          interface_m_axis_tdata;
    assign m_axis_tvalid = result_response_valid || interface_m_axis_tvalid;
    assign m_axis_tlast = result_response_valid ? 1'b1 : interface_m_axis_tlast;

    axis_interface interface_i (
        .clk(clk),
        .rst(rst),
        .s_axis_tdata(s_axis_tdata),
        .s_axis_tvalid(s_axis_tvalid),
        .s_axis_tready(s_axis_tready),
        .s_axis_tlast(s_axis_tlast),
        .m_axis_tdata(interface_m_axis_tdata),
        .m_axis_tvalid(interface_m_axis_tvalid),
        .m_axis_tready(m_axis_tready && !result_response_valid),
        .m_axis_tlast(interface_m_axis_tlast),
        .config_reg(interface_config_reg)
    );

    compute_core #(
        .TAPS(TAPS),
        .DATA_WIDTH(DATA_WIDTH),
        .ACC_WIDTH(ACC_WIDTH)
    ) compute_i (
        .clk(clk),
        .rst(rst),
        .start(start),
        .activations(activations),
        .weights(weights),
        .bias(bias),
        .busy(compute_busy),
        .done(compute_done),
        .result(result)
    );

    always_ff @(posedge clk) begin
        if (rst) begin
            activations <= '0;
            weights <= '0;
            bias <= '0;
            start <= 1'b0;
            result_latched <= '0;
            result_valid <= 1'b0;
            result_response_valid <= 1'b0;
        end else begin
            start <= 1'b0;

            if (compute_done) begin
                result_latched <= result;
                result_valid <= 1'b1;
            end

            if (result_response_valid && m_axis_tready) begin
                result_response_valid <= 1'b0;
            end

            if (command_handshake) begin
                case (subcommand)
                    CMD_LOAD_ACTIVATION: begin
                        if (tap_index < TAPS[3:0]) begin
                            activations[tap_index*DATA_WIDTH +: DATA_WIDTH] <= data_byte;
                        end
                    end

                    CMD_LOAD_WEIGHT: begin
                        if (tap_index < TAPS[3:0]) begin
                            weights[tap_index*DATA_WIDTH +: DATA_WIDTH] <= data_byte;
                        end
                    end

                    CMD_LOAD_BIAS_LO: begin
                        bias[15:0] <= s_axis_tdata[15:0];
                    end

                    CMD_LOAD_BIAS_HI: begin
                        bias[31:16] <= s_axis_tdata[15:0];
                    end

                    CMD_START: begin
                        if (!compute_busy) begin
                            start <= 1'b1;
                            result_valid <= 1'b0;
                        end
                    end

                    CMD_READ_RESULT: begin
                        if (result_valid && !result_response_valid) begin
                            result_response_valid <= 1'b1;
                        end
                    end

                    default: begin
                    end
                endcase
            end
        end
    end

endmodule

project/m3/tb/tb_top.sv
`timescale 1ns/1ps

module tb_top;
    localparam int TAPS = 9;
    localparam int DATA_WIDTH = 8;

    localparam logic [3:0] OPCODE_WRITE_CONFIG = 4'h1;
    localparam logic [3:0] RESP_RESULT         = 4'hB;

    localparam logic [3:0] CMD_LOAD_ACTIVATION = 4'h0;
    localparam logic [3:0] CMD_LOAD_WEIGHT     = 4'h1;
    localparam logic [3:0] CMD_LOAD_BIAS_LO    = 4'h2;
    localparam logic [3:0] CMD_LOAD_BIAS_HI    = 4'h3;
    localparam logic [3:0] CMD_START           = 4'h4;
    localparam logic [3:0] CMD_READ_RESULT     = 4'h5;

    logic clk;
    logic rst;
    logic [31:0] s_axis_tdata;
    logic s_axis_tvalid;
    logic s_axis_tready;
    logic s_axis_tlast;
    logic [31:0] m_axis_tdata;
    logic m_axis_tvalid;
    logic m_axis_tready;
    logic m_axis_tlast;
    logic compute_busy;
    logic compute_done;

    logic signed [7:0] activation_ref [0:TAPS-1];
    logic signed [7:0] weight_ref [0:TAPS-1];
    logic signed [31:0] bias_ref;
    logic signed [31:0] expected;
    logic signed [31:0] observed;
    logic [31:0] response_word;
    int i;
    int timeout;

    top dut (
        .clk(clk),
        .rst(rst),
        .s_axis_tdata(s_axis_tdata),
        .s_axis_tvalid(s_axis_tvalid),
        .s_axis_tready(s_axis_tready),
        .s_axis_tlast(s_axis_tlast),
        .m_axis_tdata(m_axis_tdata),
        .m_axis_tvalid(m_axis_tvalid),
        .m_axis_tready(m_axis_tready),
        .m_axis_tlast(m_axis_tlast),
        .compute_busy(compute_busy),
        .compute_done(compute_done)
    );

    initial begin
        clk = 1'b0;
        forever #5 clk = ~clk;
    end

    task automatic load_reference_vectors;
        begin
            activation_ref[0] = 8'sd3;
            activation_ref[1] = -8'sd2;
            activation_ref[2] = 8'sd7;
            activation_ref[3] = 8'sd0;
            activation_ref[4] = 8'sd5;
            activation_ref[5] = -8'sd4;
            activation_ref[6] = 8'sd9;
            activation_ref[7] = 8'sd1;
            activation_ref[8] = -8'sd8;

            weight_ref[0] = 8'sd2;
            weight_ref[1] = 8'sd6;
            weight_ref[2] = -8'sd3;
            weight_ref[3] = 8'sd4;
            weight_ref[4] = -8'sd1;
            weight_ref[5] = 8'sd5;
            weight_ref[6] = 8'sd0;
            weight_ref[7] = -8'sd7;
            weight_ref[8] = 8'sd8;
        end
    endtask

    task automatic compute_expected;
        begin
            expected = bias_ref;
            for (i = 0; i < TAPS; i = i + 1) begin
                expected = expected + (activation_ref[i] * weight_ref[i]);
            end
        end
    endtask

    task automatic host_write(input logic [3:0] subcommand,
                              input logic [3:0] tap,
                              input logic [15:0] payload);
        begin
            @(negedge clk);
            s_axis_tdata = {OPCODE_WRITE_CONFIG, subcommand, tap, 4'd0, payload};
            s_axis_tlast = 1'b1;
            s_axis_tvalid = 1'b1;

            do begin
                @(posedge clk);
                #1;
            end while (!s_axis_tready);

            @(negedge clk);
            s_axis_tvalid = 1'b0;
            s_axis_tlast = 1'b0;
            s_axis_tdata = 32'd0;
        end
    endtask

    initial begin
        $dumpfile("project/m3/sim/top.vcd");
        $dumpvars(0, tb_top);

        rst = 1'b1;
        s_axis_tdata = 32'd0;
        s_axis_tvalid = 1'b0;
        s_axis_tlast = 1'b0;
        m_axis_tready = 1'b0;
        bias_ref = 32'sd13;
        load_reference_vectors();
        compute_expected();

        repeat (2) @(posedge clk);
        @(negedge clk);
        rst = 1'b0;

        for (i = 0; i < TAPS; i = i + 1) begin
            host_write(CMD_LOAD_ACTIVATION, i[3:0], {8'd0, activation_ref[i]});
        end

        for (i = 0; i < TAPS; i = i + 1) begin
            host_write(CMD_LOAD_WEIGHT, i[3:0], {8'd0, weight_ref[i]});
        end

        host_write(CMD_LOAD_BIAS_LO, 4'd0, bias_ref[15:0]);
        host_write(CMD_LOAD_BIAS_HI, 4'd0, bias_ref[31:16]);
        host_write(CMD_START, 4'd0, 16'd0);

        timeout = 0;
        while (!compute_done && timeout < 30) begin
            @(posedge clk);
            #1;
            timeout = timeout + 1;
        end

        if (!compute_done) begin
            $display("FAIL: integrated top did not assert compute_done before timeout");
            $finish;
        end

        @(posedge clk);
        #1;
        host_write(CMD_READ_RESULT, 4'd0, 16'd0);

        timeout = 0;
        while (!m_axis_tvalid && timeout < 10) begin
            @(posedge clk);
            #1;
            timeout = timeout + 1;
        end

        if (!m_axis_tvalid || !m_axis_tlast || m_axis_tdata[31:28] !== RESP_RESULT) begin
            $display("FAIL: result response invalid valid=%b last=%b data=%h",
                     m_axis_tvalid, m_axis_tlast, m_axis_tdata);
            $finish;
        end

        observed = {{4{m_axis_tdata[27]}}, m_axis_tdata[27:0]};
        response_word = m_axis_tdata;
        m_axis_tready = 1'b1;
        @(posedge clk);
        #1;
        m_axis_tready = 1'b0;

        $display("Host programmed 9 activation taps, 9 weight taps, and bias over AXI4-Stream");
        $display("Representative 3x3 INT8 dot product expected=%0d observed=%0d response=%h",
                 expected, observed, response_word);

        if (observed !== expected) begin
            $display("FAIL: integrated top result mismatch");
            $finish;
        end

        $display("PASS: m3 end-to-end cosim");
        $finish;
    end
endmodule

project/m3/sim/top.vcd
$date
	Sun May 31 01:39:04 2026
$end
$version
	Icarus Verilog
$end
$timescale
	1ps
$end
$scope module tb_top $end
$var wire 1 ! s_axis_tready $end
$var wire 1 " m_axis_tvalid $end
$var wire 1 # m_axis_tlast $end
$var wire 32 $ m_axis_tdata [31:0] $end
$var wire 1 % compute_done $end
$var wire 1 & compute_busy $end
$var parameter 4 ' CMD_LOAD_ACTIVATION $end
$var parameter 4 ( CMD_LOAD_BIAS_HI $end
$var parameter 4 ) CMD_LOAD_BIAS_LO $end
$var parameter 4 * CMD_LOAD_WEIGHT $end
$var parameter 4 + CMD_READ_RESULT $end
$var parameter 4 , CMD_START $end
$var parameter 32 - DATA_WIDTH $end
$var parameter 4 . OPCODE_WRITE_CONFIG $end
$var parameter 4 / RESP_RESULT $end
$var parameter 32 0 TAPS $end
$var reg 32 1 bias_ref [31:0] $end
$var reg 1 2 clk $end
$var reg 32 3 expected [31:0] $end
$var reg 1 4 m_axis_tready $end
$var reg 32 5 observed [31:0] $end
$var reg 32 6 response_word [31:0] $end
$var reg 1 7 rst $end
$var reg 32 8 s_axis_tdata [31:0] $end
$var reg 1 9 s_axis_tlast $end
$var reg 1 : s_axis_tvalid $end
$var integer 32 ; i [31:0] $end
$var integer 32 < timeout [31:0] $end
$scope module dut $end
$var wire 1 2 clk $end
$var wire 1 = command_handshake $end
$var wire 1 4 m_axis_tready $end
$var wire 1 " m_axis_tvalid $end
$var wire 1 7 rst $end
$var wire 32 > s_axis_tdata [31:0] $end
$var wire 1 9 s_axis_tlast $end
$var wire 1 : s_axis_tvalid $end
$var wire 4 ? tap_index [3:0] $end
$var wire 4 @ subcommand [3:0] $end
$var wire 1 ! s_axis_tready $end
$var wire 32 A result [31:0] $end
$var wire 4 B opcode [3:0] $end
$var wire 1 # m_axis_tlast $end
$var wire 32 C m_axis_tdata [31:0] $end
$var wire 1 D interface_m_axis_tvalid $end
$var wire 1 E interface_m_axis_tlast $end
$var wire 32 F interface_m_axis_tdata [31:0] $end
$var wire 28 G interface_config_reg [27:0] $end
$var wire 8 H data_byte [7:0] $end
$var wire 1 % compute_done $end
$var wire 1 & compute_busy $end
$var parameter 32 I ACC_WIDTH $end
$var parameter 4 J CMD_LOAD_ACTIVATION $end
$var parameter 4 K CMD_LOAD_BIAS_HI $end
$var parameter 4 L CMD_LOAD_BIAS_LO $end
$var parameter 4 M CMD_LOAD_WEIGHT $end
$var parameter 4 N CMD_READ_RESULT $end
$var parameter 4 O CMD_START $end
$var parameter 32 P DATA_WIDTH $end
$var parameter 4 Q OPCODE_WRITE_CONFIG $end
$var parameter 4 R RESP_RESULT $end
$var parameter 32 S TAPS $end
$var reg 72 T activations [71:0] $end
$var reg 32 U bias [31:0] $end
$var reg 32 V result_latched [31:0] $end
$var reg 1 W result_response_valid $end
$var reg 1 X result_valid $end
$var reg 1 Y start $end
$var reg 72 Z weights [71:0] $end
$scope module compute_i $end
$var wire 72 [ activations [71:0] $end
$var wire 32 \ bias [31:0] $end
$var wire 1 2 clk $end
$var wire 1 7 rst $end
$var wire 1 Y start $end
$var wire 72 ] weights [71:0] $end
$var wire 8 ^ weight_tap [7:0] $end
$var wire 32 _ product_ext [31:0] $end
$var wire 16 ` product [15:0] $end
$var wire 32 a next_accumulator [31:0] $end
$var wire 8 b activation_tap [7:0] $end
$var parameter 32 c ACC_WIDTH $end
$var parameter 32 d DATA_WIDTH $end
$var parameter 32 e TAPS $end
$var parameter 32 f TAP_INDEX_WIDTH $end
$var reg 32 g accumulator [31:0] $end
$var reg 1 & busy $end
$var reg 1 % done $end
$var reg 32 h result [31:0] $end
$var reg 4 i tap_index [3:0] $end
$upscope $end
$scope module interface_i $end
$var wire 1 2 clk $end
$var wire 1 j input_handshake $end
$var wire 1 k m_axis_tready $end
$var wire 1 l output_handshake $end
$var wire 1 7 rst $end
$var wire 32 m s_axis_tdata [31:0] $end
$var wire 1 9 s_axis_tlast $end
$var wire 1 : s_axis_tvalid $end
$var wire 1 ! s_axis_tready $end
$var wire 28 n payload [27:0] $end
$var wire 4 o opcode [3:0] $end
$var parameter 4 p OPCODE_READ_CONFIG $end
$var parameter 4 q OPCODE_RESPONSE $end
$var parameter 4 r OPCODE_WRITE_CONFIG $end
$var reg 28 s config_reg [27:0] $end
$var reg 32 t m_axis_tdata [31:0] $end
$var reg 1 E m_axis_tlast $end
$var reg 1 D m_axis_tvalid $end
$upscope $end
$upscope $end
$scope task compute_expected $end
$upscope $end
$scope task host_write $end
$upscope $end
$scope task load_reference_vectors $end
$upscope $end
$upscope $end
$enddefinitions $end
$comment Show the parameter values. $end
$dumpall
b1 r
b1010 q
b10 p
b100 f
b1001 e
b1000 d
b100000 c
b1001 S
b1011 R
b1 Q
b1000 P
b100 O
b101 N
b1 M
b10 L
b11 K
b0 J
b100000 I
b1001 0
b1011 /
b1 .
b1000 -
b100 ,
b101 +
b1 *
b10 )
b11 (
b0 '
$end
#0
$dumpvars
bx t
bx s
b0 o
b0 n
b0 m
0l
0k
0j
bx i
bx h
bx g
bx b
bx a
bx `
bx _
bx ^
bx ]
bx \
bx [
bx Z
xY
xX
xW
bx V
bx U
bx T
b0 H
bx G
bx F
xE
xD
bx C
b0 B
bx A
b0 @
b0 ?
b0 >
0=
b0 <
b1001 ;
0:
09
b0 8
17
bx 6
bx 5
04
b11111111111111111111111110010010 3
02
b1101 1
x&
x%
bx $
x#
x"
x!
$end
#5000
b0 a
b0 _
b0 `
b0 b
b0 ^
b0 $
b0 C
0#
0"
0E
1!
0D
b0 F
b0 t
b0 G
b0 s
0%
0&
b0 A
b0 h
b0 g
b0 i
0W
0X
b0 V
0Y
b0 U
b0 \
b0 Z
b0 ]
b0 T
b0 [
12
#10000
02
#15000
12
#20000
b0 ;
07
02
#25000
12
#30000
1=
1j
b1 B
b11 H
b1 o
b11 n
1:
19
b10000000000000000000000000011 8
b10000000000000000000000000011 >
b10000000000000000000000000011 m
02
#35000
b11 b
b11 T
b11 [
b11 G
b11 s
12
#40000
0=
b0 B
b0 H
b0 o
b0 n
0j
b1 ;
b0 8
b0 >
b0 m
09
0:
02
#45000
12
#50000
1=
1j
b1 B
b1 ?
b11111110 H
b1 o
b100000000000011111110 n
1:
19
b10000000100000000000011111110 8
b10000000100000000000011111110 >
b10000000100000000000011111110 m
02
#55000
b1111111000000011 T
b1111111000000011 [
b100000000000011111110 G
b100000000000011111110 s
12
#60000
0=
b0 B
b0 ?
b0 H
b0 o
b0 n
0j
b10 ;
b0 8
b0 >
b0 m
09
0:
02
#65000
12
#70000
1=
1j
b1 B
b10 ?
b111 H
b1 o
b1000000000000000000111 n
1:
19
b10000001000000000000000000111 8
b10000001000000000000000000111 >
b10000001000000000000000000111 m
02
#75000
b1111111111000000011 T
b1111111111000000011 [
b1000000000000000000111 G
b1000000000000000000111 s
12
#80000
0=
b0 B
b0 ?
b0 H
b0 o
b0 n
0j
b11 ;
b0 8
b0 >
b0 m
09
0:
02
#85000
12
#90000
1=
1j
b1 B
b11 ?
b1 o
b1100000000000000000000 n
1:
19
b10000001100000000000000000000 8
b10000001100000000000000000000 >
b10000001100000000000000000000 m
02
#95000
b1100000000000000000000 G
b1100000000000000000000 s
12
#100000
0=
b0 B
b0 ?
b0 o
b0 n
0j
b100 ;
b0 8
b0 >
b0 m
09
0:
02
#105000
12
#110000
1=
1j
b1 B
b100 ?
b101 H
b1 o
b10000000000000000000101 n
1:
19
b10000010000000000000000000101 8
b10000010000000000000000000101 >
b10000010000000000000000000101 m
02
#115000
b10100000000000001111111111000000011 T
b10100000000000001111111111000000011 [
b10000000000000000000101 G
b10000000000000000000101 s
12
#120000
0=
b0 B
b0 ?
b0 H
b0 o
b0 n
0j
b101 ;
b0 8
b0 >
b0 m
09
0:
02
#125000
12
#130000
1=
1j
b1 B
b101 ?
b11111100 H
b1 o
b10100000000000011111100 n
1:
19
b10000010100000000000011111100 8
b10000010100000000000011111100 >
b10000010100000000000011111100 m
02
#135000
b111111000000010100000000000001111111111000000011 T
b111111000000010100000000000001111111111000000011 [
b10100000000000011111100 G
b10100000000000011111100 s
12
#140000
0=
b0 B
b0 ?
b0 H
b0 o
b0 n
0j
b110 ;
b0 8
b0 >
b0 m
09
0:
02
#145000
12
#150000
1=
1j
b1 B
b110 ?
b1001 H
b1 o
b11000000000000000001001 n
1:
19
b10000011000000000000000001001 8
b10000011000000000000000001001 >
b10000011000000000000000001001 m
02
#155000
b1001111111000000010100000000000001111111111000000011 T
b1001111111000000010100000000000001111111111000000011 [
b11000000000000000001001 G
b11000000000000000001001 s
12
#160000
0=
b0 B
b0 ?
b0 H
b0 o
b0 n
0j
b111 ;
b0 8
b0 >
b0 m
09
0:
02
#165000
12
#170000
1=
1j
b1 B
b111 ?
b1 H
b1 o
b11100000000000000000001 n
1:
19
b10000011100000000000000000001 8
b10000011100000000000000000001 >
b10000011100000000000000000001 m
02
#175000
b100001001111111000000010100000000000001111111111000000011 T
b100001001111111000000010100000000000001111111111000000011 [
b11100000000000000000001 G
b11100000000000000000001 s
12
#180000
0=
b0 B
b0 ?
b0 H
b0 o
b0 n
0j
b1000 ;
b0 8
b0 >
b0 m
09
0:
02
#185000
12
#190000
1=
1j
b1 B
b1000 ?
b11111000 H
b1 o
b100000000000000011111000 n
1:
19
b10000100000000000000011111000 8
b10000100000000000000011111000 >
b10000100000000000000011111000 m
02
#195000
b111110000000000100001001111111000000010100000000000001111111111000000011 T
b111110000000000100001001111111000000010100000000000001111111111000000011 [
b100000000000000011111000 G
b100000000000000011111000 s
12
#200000
0=
b0 B
b0 ?
b0 H
b0 o
b0 n
0j
b0 ;
b0 8
b0 >
b0 m
09
0:
02
#205000
12
#210000
1=
1j
b1 B
b1 @
b10 H
b1 o
b1000000000000000000000010 n
1:
19
b10001000000000000000000000010 8
b10001000000000000000000000010 >
b10001000000000000000000000010 m
02
#215000
b110 a
b110 _
b110 `
b10 ^
b10 Z
b10 ]
b1000000000000000000000010 G
b1000000000000000000000010 s
12
#220000
0=
b0 B
b0 @
b0 H
b0 o
b0 n
0j
b1 ;
b0 8
b0 >
b0 m
09
0:
02
#225000
12
#230000
1=
1j
b1 B
b1 @
b1 ?
b110 H
b1 o
b1000100000000000000000110 n
1:
19
b10001000100000000000000000110 8
b10001000100000000000000000110 >
b10001000100000000000000000110 m
02
#235000
b11000000010 Z
b11000000010 ]
b1000100000000000000000110 G
b1000100000000000000000110 s
12
#240000
0=
b0 B
b0 @
b0 ?
b0 H
b0 o
b0 n
0j
b10 ;
b0 8
b0 >
b0 m
09
0:
02
#245000
12
#250000
1=
1j
b1 B
b1 @
b10 ?
b11111101 H
b1 o
b1001000000000000011111101 n
1:
19
b10001001000000000000011111101 8
b10001001000000000000011111101 >
b10001001000000000000011111101 m
02
#255000
b111111010000011000000010 Z
b111111010000011000000010 ]
b1001000000000000011111101 G
b1001000000000000011111101 s
12
#260000
0=
b0 B
b0 @
b0 ?
b0 H
b0 o
b0 n
0j
b11 ;
b0 8
b0 >
b0 m
09
0:
02
#265000
12
#270000
1=
1j
b1 B
b1 @
b11 ?
b100 H
b1 o
b1001100000000000000000100 n
1:
19
b10001001100000000000000000100 8
b10001001100000000000000000100 >
b10001001100000000000000000100 m
02
#275000
b100111111010000011000000010 Z
b100111111010000011000000010 ]
b1001100000000000000000100 G
b1001100000000000000000100 s
12
#280000
0=
b0 B
b0 @
b0 ?
b0 H
b0 o
b0 n
0j
b100 ;
b0 8
b0 >
b0 m
09
0:
02
#285000
12
#290000
1=
1j
b1 B
b1 @
b100 ?
b11111111 H
b1 o
b1010000000000000011111111 n
1:
19
b10001010000000000000011111111 8
b10001010000000000000011111111 >
b10001010000000000000011111111 m
02
#295000
b1111111100000100111111010000011000000010 Z
b1111111100000100111111010000011000000010 ]
b1010000000000000011111111 G
b1010000000000000011111111 s
12
#300000
0=
b0 B
b0 @
b0 ?
b0 H
b0 o
b0 n
0j
b101 ;
b0 8
b0 >
b0 m
09
0:
02
#305000
12
#310000
1=
1j
b1 B
b1 @
b101 ?
b101 H
b1 o
b1010100000000000000000101 n
1:
19
b10001010100000000000000000101 8
b10001010100000000000000000101 >
b10001010100000000000000000101 m
02
#315000
b1011111111100000100111111010000011000000010 Z
b1011111111100000100111111010000011000000010 ]
b1010100000000000000000101 G
b1010100000000000000000101 s
12
#320000
0=
b0 B
b0 @
b0 ?
b0 H
b0 o
b0 n
0j
b110 ;
b0 8
b0 >
b0 m
09
0:
02
#325000
12
#330000
1=
1j
b1 B
b1 @
b110 ?
b1 o
b1011000000000000000000000 n
1:
19
b10001011000000000000000000000 8
b10001011000000000000000000000 >
b10001011000000000000000000000 m
02
#335000
b1011000000000000000000000 G
b1011000000000000000000000 s
12
